envialosimple/transaccional/__init__.py
envialosimple/transaccional/endpoints.py
envialosimple/transaccional/errors.py
envialosimple/transaccional/http.py
envialosimple/transaccional/mail.py
envialosimple_transaccional-0.2.0.dist-info/METADATA
envialosimple_transaccional-0.2.0.dist-info/WHEEL
envialosimple_transaccional-0.2.0.dist-info/RECORD
