Metadata-Version: 2.1
Name: envialosimple-transaccional
Version: 0.2.0
Summary: Python SDK for EnvíaloSimple Transaccional
Author: Daniel Libonati
Author-email: daniel.libonati@donweb.com
Requires-Python: >=3.8,<4.0
Classifier: Programming Language :: Python :: 3
Classifier: Programming Language :: Python :: 3.8
Classifier: Programming Language :: Python :: 3.9
Classifier: Programming Language :: Python :: 3.10
Classifier: Programming Language :: Python :: 3.11
Classifier: Programming Language :: Python :: 3.12
Requires-Dist: requests (>=2.31.0,<3.0.0)
Requires-Dist: typing-extensions (>=4.8.0,<5.0.0)
